{
  "timestamp": "2026-04-04T13:22:47.634884+00:00",
  "description": "Proposition-to-qubit circuits: GPT-2 layer trajectories encoded as Bloch sphere rotations",
  "model": "gpt2 (124M, 13 layers)",
  "method": "last-token hidden state at each layer -> PCA to 2D -> Bloch angles -> rz/ry gates",
  "circuits": [
    {
      "circuit_name": "proposition_curvature",
      "text": "The proposition lives in the curvature. The serialization is the scar.",
      "qasm": "OPENQASM 2.0;\ninclude \"qelib1.inc\";\nqreg q[1];\ncreg c[1];\nh q[0];\n// Proposition-to-qubit: hidden state layer trajectory: 13 steps from weight trajectory PCA\nrz(2.329963) q[0];\nry(0.902152) q[0];\nrz(2.657873) q[0];\nry(0.655174) q[0];\nrz(2.642466) q[0];\nry(0.655768) q[0];\nrz(2.667060) q[0];\nry(0.635982) q[0];\nrz(2.663964) q[0];\nry(0.620335) q[0];\nrz(2.755828) q[0];\nry(0.567127) q[0];\nrz(2.863245) q[0];\nry(0.507124) q[0];\nrz(-3.031150) q[0];\nry(0.415148) q[0];\nrz(-2.503979) q[0];\nry(0.364837) q[0];\nrz(-1.615972) q[0];\nry(0.651736) q[0];\nrz(-1.264005) q[0];\nry(1.214803) q[0];\nrz(-0.835542) q[0];\nry(2.362531) q[0];\nrz(0.542813) q[0];\nry(3.141593) q[0];\nh q[0];\nmeasure q[0] -> c[0];",
      "n_gates": 26
    },
    {
      "circuit_name": "proposition_lawyer_runner",
      "text": "She is a lawyer and a runner.",
      "qasm": "OPENQASM 2.0;\ninclude \"qelib1.inc\";\nqreg q[1];\ncreg c[1];\nh q[0];\n// Proposition-to-qubit: hidden state layer trajectory: 13 steps from weight trajectory PCA\nrz(2.240191) q[0];\nry(0.906812) q[0];\nrz(2.584348) q[0];\nry(0.636369) q[0];\nrz(2.541621) q[0];\nry(0.657747) q[0];\nrz(2.565363) q[0];\nry(0.635131) q[0];\nrz(2.625936) q[0];\nry(0.585840) q[0];\nrz(2.683163) q[0];\nry(0.545141) q[0];\nrz(2.834676) q[0];\nry(0.476944) q[0];\nrz(-3.048529) q[0];\nry(0.387379) q[0];\nrz(-2.428113) q[0];\nry(0.368532) q[0];\nrz(-1.712717) q[0];\nry(0.600779) q[0];\nrz(-1.374094) q[0];\nry(1.121413) q[0];\nrz(-0.948273) q[0];\nry(2.349853) q[0];\nrz(0.476671) q[0];\nry(3.141593) q[0];\nh q[0];\nmeasure q[0] -> c[0];",
      "n_gates": 26
    },
    {
      "circuit_name": "proposition_runner_lawyer",
      "text": "She is a runner and a lawyer.",
      "qasm": "OPENQASM 2.0;\ninclude \"qelib1.inc\";\nqreg q[1];\ncreg c[1];\nh q[0];\n// Proposition-to-qubit: hidden state layer trajectory: 13 steps from weight trajectory PCA\nrz(2.227784) q[0];\nry(0.897672) q[0];\nrz(2.564400) q[0];\nry(0.636691) q[0];\nrz(2.523184) q[0];\nry(0.656671) q[0];\nrz(2.552888) q[0];\nry(0.631635) q[0];\nrz(2.618283) q[0];\nry(0.582872) q[0];\nrz(2.667705) q[0];\nry(0.552335) q[0];\nrz(2.817662) q[0];\nry(0.482246) q[0];\nrz(-3.055331) q[0];\nry(0.387599) q[0];\nrz(-2.427688) q[0];\nry(0.368080) q[0];\nrz(-1.720898) q[0];\nry(0.610189) q[0];\nrz(-1.381371) q[0];\nry(1.116155) q[0];\nrz(-0.961521) q[0];\nry(2.296808) q[0];\nrz(0.451576) q[0];\nry(3.141593) q[0];\nh q[0];\nmeasure q[0] -> c[0];",
      "n_gates": 26
    },
    {
      "circuit_name": "proposition_dog_bit_man",
      "text": "The dog bit the man.",
      "qasm": "OPENQASM 2.0;\ninclude \"qelib1.inc\";\nqreg q[1];\ncreg c[1];\nh q[0];\n// Proposition-to-qubit: hidden state layer trajectory: 13 steps from weight trajectory PCA\nrz(2.874299) q[0];\nry(1.056054) q[0];\nrz(-3.022603) q[0];\nry(0.689232) q[0];\nrz(-3.072853) q[0];\nry(0.731010) q[0];\nrz(-3.073353) q[0];\nry(0.724181) q[0];\nrz(-3.049599) q[0];\nry(0.696805) q[0];\nrz(-2.921005) q[0];\nry(0.609295) q[0];\nrz(-2.674671) q[0];\nry(0.497284) q[0];\nrz(-2.296320) q[0];\nry(0.410599) q[0];\nrz(-1.693081) q[0];\nry(0.395859) q[0];\nrz(-0.934036) q[0];\nry(0.682867) q[0];\nrz(-0.600243) q[0];\nry(1.271536) q[0];\nrz(-0.246268) q[0];\nry(2.905750) q[0];\nrz(1.268770) q[0];\nry(3.141593) q[0];\nh q[0];\nmeasure q[0] -> c[0];",
      "n_gates": 26
    },
    {
      "circuit_name": "proposition_man_bit_dog",
      "text": "The man bit the dog.",
      "qasm": "OPENQASM 2.0;\ninclude \"qelib1.inc\";\nqreg q[1];\ncreg c[1];\nh q[0];\n// Proposition-to-qubit: hidden state layer trajectory: 13 steps from weight trajectory PCA\nrz(2.934321) q[0];\nry(1.064333) q[0];\nrz(-2.958792) q[0];\nry(0.682535) q[0];\nrz(-3.006655) q[0];\nry(0.725337) q[0];\nrz(-2.995673) q[0];\nry(0.711931) q[0];\nrz(-2.967526) q[0];\nry(0.686492) q[0];\nrz(-2.856994) q[0];\nry(0.618100) q[0];\nrz(-2.670985) q[0];\nry(0.527631) q[0];\nrz(-2.322315) q[0];\nry(0.429503) q[0];\nrz(-1.652279) q[0];\nry(0.392029) q[0];\nrz(-0.881890) q[0];\nry(0.664219) q[0];\nrz(-0.542831) q[0];\nry(1.328341) q[0];\nrz(-0.175495) q[0];\nry(2.989866) q[0];\nrz(1.347063) q[0];\nry(3.141593) q[0];\nh q[0];\nmeasure q[0] -> c[0];",
      "n_gates": 26
    },
    {
      "circuit_name": "proposition_empata",
      "text": "Eppur si empata.",
      "qasm": "OPENQASM 2.0;\ninclude \"qelib1.inc\";\nqreg q[1];\ncreg c[1];\nh q[0];\n// Proposition-to-qubit: hidden state layer trajectory: 13 steps from weight trajectory PCA\nrz(3.093387) q[0];\nry(0.999500) q[0];\nrz(2.711001) q[0];\nry(0.650792) q[0];\nrz(2.774730) q[0];\nry(0.710322) q[0];\nrz(2.757051) q[0];\nry(0.686458) q[0];\nrz(2.722665) q[0];\nry(0.661327) q[0];\nrz(2.622822) q[0];\nry(0.598802) q[0];\nrz(2.521983) q[0];\nry(0.535683) q[0];\nrz(2.118164) q[0];\nry(0.403162) q[0];\nrz(1.215364) q[0];\nry(0.416395) q[0];\nrz(0.693187) q[0];\nry(0.645772) q[0];\nrz(0.329493) q[0];\nry(1.352118) q[0];\nrz(-0.054092) q[0];\nry(2.973037) q[0];\nrz(-1.644240) q[0];\nry(3.141593) q[0];\nh q[0];\nmeasure q[0] -> c[0];",
      "n_gates": 26
    },
    {
      "circuit_name": "proposition_abundance",
      "text": "Intelligence abundance restructures the relationship between people and the law.",
      "qasm": "OPENQASM 2.0;\ninclude \"qelib1.inc\";\nqreg q[1];\ncreg c[1];\nh q[0];\n// Proposition-to-qubit: hidden state layer trajectory: 13 steps from weight trajectory PCA\nrz(2.172622) q[0];\nry(0.811055) q[0];\nrz(2.497941) q[0];\nry(0.599025) q[0];\nrz(2.479482) q[0];\nry(0.591154) q[0];\nrz(2.501022) q[0];\nry(0.571846) q[0];\nrz(2.537850) q[0];\nry(0.546054) q[0];\nrz(2.646291) q[0];\nry(0.497038) q[0];\nrz(2.777926) q[0];\nry(0.437583) q[0];\nrz(-3.140747) q[0];\nry(0.381420) q[0];\nrz(-2.585992) q[0];\nry(0.375319) q[0];\nrz(-1.985566) q[0];\nry(0.548691) q[0];\nrz(-1.538480) q[0];\nry(0.959632) q[0];\nrz(-1.015556) q[0];\nry(1.971461) q[0];\nrz(0.290463) q[0];\nry(3.141593) q[0];\nh q[0];\nmeasure q[0] -> c[0];",
      "n_gates": 26
    }
  ]
}