{
  "timestamp": "2026-03-24T11:33:45.378484+00:00",
  "description": "Cross-architecture sign invariance test: GPT-2 vs Pythia-160M",
  "paper": "substrate_orthogonality.md, Experiment 1 / Conjecture 4.1",
  "models": {
    "gpt2": {
      "name": "gpt2",
      "params": "124M",
      "n_layers": 12,
      "hidden_dim": 768,
      "architecture": "GPT-2 (learned positional embeddings, BPE tokenizer)"
    },
    "pythia": {
      "name": "EleutherAI/pythia-160m",
      "params": "160M",
      "n_layers": 12,
      "hidden_dim": 768,
      "architecture": "Pythia (rotary embeddings, Neox tokenizer)"
    }
  },
  "layer_pairs": [
    "L0->L3",
    "L0->L6",
    "L3->L9",
    "L6->L12"
  ],
  "concept_classes": [
    "temporal",
    "epistemic",
    "relational",
    "embodied",
    "abstract",
    "existential"
  ],
  "gpt2_sgp": {
    "temporal": {
      "L0->L3": {
        "mean_phase_rad": -4.525085214843191,
        "sgp_sign": -1,
        "std": 3.363139573816685,
        "n_prompts": 4,
        "phases": [
          0.9456496936158627,
          -5.943866778113886,
          -8.146647462263521,
          -4.955476312611218
        ]
      },
      "L0->L6": {
        "mean_phase_rad": -5.5014880361688245,
        "sgp_sign": -1,
        "std": 3.1798980710415075,
        "n_prompts": 4,
        "phases": [
          -0.9720537725195701,
          -7.471946640135105,
          -9.308261652854018,
          -4.253690079166601
        ]
      },
      "L3->L9": {
        "mean_phase_rad": 0.018665161825341784,
        "sgp_sign": 1,
        "std": 0.07931696279275673,
        "n_prompts": 4,
        "phases": [
          -0.07336201988281105,
          0.026714046290981584,
          0.14160107822798562,
          -0.02029245733478903
        ]
      },
      "L6->L12": {
        "mean_phase_rad": 0.2554258083976725,
        "sgp_sign": 1,
        "std": 0.35585307540956995,
        "n_prompts": 4,
        "phases": [
          0.22950510707281405,
          0.08803638348162268,
          0.8312207990597895,
          -0.1270590560235364
        ]
      }
    },
    "epistemic": {
      "L0->L3": {
        "mean_phase_rad": -4.526604252700383,
        "sgp_sign": -1,
        "std": 2.064459203800663,
        "n_prompts": 4,
        "phases": [
          -5.773333626395518,
          -0.9517953130501215,
          -5.737531654952498,
          -5.643756416403394
        ]
      },
      "L0->L6": {
        "mean_phase_rad": -1.2612019821275495,
        "sgp_sign": -1,
        "std": 2.4368101609617443,
        "n_prompts": 4,
        "phases": [
          -1.3889935011504815,
          0.36972397052797057,
          1.1452537857809446,
          -5.170792183668632
        ]
      },
      "L3->L9": {
        "mean_phase_rad": -0.022862596944310358,
        "sgp_sign": -1,
        "std": 0.012286088388453586,
        "n_prompts": 4,
        "phases": [
          -0.03418837917876877,
          -0.035345313948477036,
          -0.006699357625005287,
          -0.015217337024990344
        ]
      },
      "L6->L12": {
        "mean_phase_rad": 0.3369473646028329,
        "sgp_sign": 1,
        "std": 0.4031279925010544,
        "n_prompts": 4,
        "phases": [
          0.2786846521709902,
          0.6876296988856385,
          0.6811055035333945,
          -0.2996303961786917
        ]
      }
    },
    "relational": {
      "L0->L3": {
        "mean_phase_rad": 0.8096942734171539,
        "sgp_sign": 1,
        "std": 2.0048135197188257,
        "n_prompts": 4,
        "phases": [
          1.2739000830393692,
          0.8121054639700188,
          3.382873830977147,
          -2.23010228431792
        ]
      },
      "L0->L6": {
        "mean_phase_rad": 3.7265287307268222,
        "sgp_sign": 1,
        "std": 3.079017994181975,
        "n_prompts": 4,
        "phases": [
          2.8262676451878654,
          2.996345190242554,
          8.739881244779824,
          0.3436208426970453
        ]
      },
      "L3->L9": {
        "mean_phase_rad": 0.06491430035596063,
        "sgp_sign": 1,
        "std": 0.02527390167542835,
        "n_prompts": 4,
        "phases": [
          0.07944460588684558,
          0.06345543159387124,
          0.09196720442851025,
          0.024789959514615434
        ]
      },
      "L6->L12": {
        "mean_phase_rad": 0.8200899936985478,
        "sgp_sign": 1,
        "std": 2.430527797957353,
        "n_prompts": 4,
        "phases": [
          0.96922108258784,
          0.45504965782296425,
          -2.4962114024874076,
          4.352300636870795
        ]
      }
    },
    "embodied": {
      "L0->L3": {
        "mean_phase_rad": 0.04559640734338943,
        "sgp_sign": 1,
        "std": 3.7186784970086038,
        "n_prompts": 4,
        "phases": [
          -2.3095757994153567,
          -0.49271384197645507,
          6.251095070187894,
          -3.2664197994225246
        ]
      },
      "L0->L6": {
        "mean_phase_rad": 1.027545855860813,
        "sgp_sign": 1,
        "std": 6.12496757253571,
        "n_prompts": 4,
        "phases": [
          -5.5186005770438795,
          4.2280754089841395,
          9.459382049943304,
          -4.058673458440311
        ]
      },
      "L3->L9": {
        "mean_phase_rad": 0.05406743478599036,
        "sgp_sign": 1,
        "std": 0.12479718810135722,
        "n_prompts": 4,
        "phases": [
          -0.10112215271904358,
          -0.030370323034352442,
          0.2083280035531829,
          0.13943421134417455
        ]
      },
      "L6->L12": {
        "mean_phase_rad": 0.5064044205076587,
        "sgp_sign": 1,
        "std": 0.9701968959049275,
        "n_prompts": 4,
        "phases": [
          0.9283970482290759,
          -0.8772653649647805,
          1.7650915503053954,
          0.2093944484609436
        ]
      }
    },
    "abstract": {
      "L0->L3": {
        "mean_phase_rad": -2.21113114097445,
        "sgp_sign": -1,
        "std": 2.539917048729331,
        "n_prompts": 4,
        "phases": [
          -4.372005149154561,
          -4.10626052041429,
          1.9753701328061817,
          -2.34162902713513
        ]
      },
      "L0->L6": {
        "mean_phase_rad": -0.7729238556903953,
        "sgp_sign": -1,
        "std": 3.962917924480546,
        "n_prompts": 4,
        "phases": [
          0.7431608517917417,
          -1.2923573428479187,
          4.194731374277809,
          -6.737230305983213
        ]
      },
      "L3->L9": {
        "mean_phase_rad": -0.02693922989839931,
        "sgp_sign": -1,
        "std": 0.05156380660904909,
        "n_prompts": 4,
        "phases": [
          -0.03691143383641535,
          0.029561248015282475,
          -0.10615475477173743,
          0.0057480209992730805
        ]
      },
      "L6->L12": {
        "mean_phase_rad": 0.9163484595340661,
        "sgp_sign": 1,
        "std": 2.256839045489761,
        "n_prompts": 4,
        "phases": [
          1.352086463400489,
          -2.4446493481504348,
          3.8969611640133675,
          0.8609955588728428
        ]
      }
    },
    "existential": {
      "L0->L3": {
        "mean_phase_rad": -0.39498001993586646,
        "sgp_sign": -1,
        "std": 1.6495703153460577,
        "n_prompts": 4,
        "phases": [
          -1.23694358440761,
          2.437956903354121,
          -1.1007192333648173,
          -1.6802141653251597
        ]
      },
      "L0->L6": {
        "mean_phase_rad": -2.3518749715072103,
        "sgp_sign": -1,
        "std": 3.9975095370150715,
        "n_prompts": 4,
        "phases": [
          0.4392932718089487,
          2.6109896126067476,
          -5.381196744763622,
          -7.076586025680916
        ]
      },
      "L3->L9": {
        "mean_phase_rad": 0.04449820927903873,
        "sgp_sign": 1,
        "std": 0.03805349573126597,
        "n_prompts": 4,
        "phases": [
          0.10841672608173362,
          0.020211926606172916,
          0.011807371982321416,
          0.03755681244592697
        ]
      },
      "L6->L12": {
        "mean_phase_rad": 1.4920497356153781,
        "sgp_sign": 1,
        "std": 0.6116178899738386,
        "n_prompts": 4,
        "phases": [
          1.992338212229553,
          1.733446110000079,
          1.7967429475343448,
          0.44567167269753616
        ]
      }
    }
  },
  "pythia_sgp": {
    "temporal": {
      "L0->L3": {
        "mean_phase_rad": 3.9236926244244152,
        "sgp_sign": 1,
        "std": 7.611809424800474,
        "n_prompts": 4,
        "phases": [
          -7.392374216361062,
          6.016909413101714,
          3.2062733073509895,
          13.863961993606019
        ]
      },
      "L0->L6": {
        "mean_phase_rad": 2.3559786231797935,
        "sgp_sign": 1,
        "std": 4.980292862176583,
        "n_prompts": 4,
        "phases": [
          -3.55197284797251,
          1.298773823693125,
          10.250755442909869,
          1.4263580740886903
        ]
      },
      "L3->L9": {
        "mean_phase_rad": 0.1679149200462185,
        "sgp_sign": 1,
        "std": 0.12421253067581241,
        "n_prompts": 4,
        "phases": [
          0.34259443825885877,
          0.028585648175283827,
          0.07552496880802702,
          0.22495462494270443
        ]
      },
      "L6->L12": {
        "mean_phase_rad": -0.9467983353947528,
        "sgp_sign": -1,
        "std": 1.4153105319803967,
        "n_prompts": 4,
        "phases": [
          1.1338573537610446,
          -0.7328271394295918,
          -1.3852931949385938,
          -2.80293036097187
        ]
      }
    },
    "epistemic": {
      "L0->L3": {
        "mean_phase_rad": -0.6053712828266629,
        "sgp_sign": -1,
        "std": 5.824866449262058,
        "n_prompts": 4,
        "phases": [
          -6.599263804802877,
          0.675607800508941,
          8.348162254674167,
          -4.845991381686882
        ]
      },
      "L0->L6": {
        "mean_phase_rad": -2.4294226351002104,
        "sgp_sign": -1,
        "std": 2.151935965418893,
        "n_prompts": 4,
        "phases": [
          -3.7517634910644713,
          1.2702563828310192,
          -3.9795021848088346,
          -3.2566812473585545
        ]
      },
      "L3->L9": {
        "mean_phase_rad": 0.06260898399073969,
        "sgp_sign": 1,
        "std": 0.11686210541870021,
        "n_prompts": 4,
        "phases": [
          0.021971738644701318,
          0.22814693010365109,
          -0.0941088498982576,
          0.09442611711286394
        ]
      },
      "L6->L12": {
        "mean_phase_rad": 2.591918525016527,
        "sgp_sign": 1,
        "std": 2.7426604183811394,
        "n_prompts": 4,
        "phases": [
          6.565991431234388,
          0.4153347576631984,
          -0.2996241676346429,
          3.685972078803163
        ]
      }
    },
    "relational": {
      "L0->L3": {
        "mean_phase_rad": -4.265483953593772,
        "sgp_sign": -1,
        "std": 2.5541968186851625,
        "n_prompts": 4,
        "phases": [
          -4.872148447774261,
          -4.830582384439349,
          -7.1954091789583146,
          -0.16379580320316123
        ]
      },
      "L0->L6": {
        "mean_phase_rad": -2.43591608026957,
        "sgp_sign": -1,
        "std": 6.0196260525956395,
        "n_prompts": 4,
        "phases": [
          -1.097208690472399,
          -6.877385449613643,
          6.816479052692184,
          -8.585549233684421
        ]
      },
      "L3->L9": {
        "mean_phase_rad": 0.14932377648698913,
        "sgp_sign": 1,
        "std": 0.05948279827315816,
        "n_prompts": 4,
        "phases": [
          0.1691173489404225,
          0.23595575598562485,
          0.11332623686059957,
          0.07889576416130961
        ]
      },
      "L6->L12": {
        "mean_phase_rad": 2.1142975890770623,
        "sgp_sign": 1,
        "std": 1.9923056083020765,
        "n_prompts": 4,
        "phases": [
          1.6220665195860753,
          1.8671859649833766,
          -0.28193572243632936,
          5.249873594175126
        ]
      }
    },
    "embodied": {
      "L0->L3": {
        "mean_phase_rad": -2.498689294306879,
        "sgp_sign": -1,
        "std": 7.291709146315478,
        "n_prompts": 4,
        "phases": [
          6.324330210287673,
          1.6404959351710544,
          -4.875636098291605,
          -13.08394722439464
        ]
      },
      "L0->L6": {
        "mean_phase_rad": -2.3737047623830723,
        "sgp_sign": -1,
        "std": 6.31578350465522,
        "n_prompts": 4,
        "phases": [
          5.278953804079076,
          0.04651332376537032,
          -2.698220744146833,
          -12.122065433229903
        ]
      },
      "L3->L9": {
        "mean_phase_rad": 0.1679458672525771,
        "sgp_sign": 1,
        "std": 0.10579651250399848,
        "n_prompts": 4,
        "phases": [
          0.299197061461836,
          0.10278549908236245,
          0.23764980952869344,
          0.03215109893741652
        ]
      },
      "L6->L12": {
        "mean_phase_rad": -0.70834087717825,
        "sgp_sign": -1,
        "std": 3.2927913750043865,
        "n_prompts": 4,
        "phases": [
          -2.9789883630333613,
          -1.2242261125626723,
          -3.442152191671712,
          4.812003158554746
        ]
      }
    },
    "abstract": {
      "L0->L3": {
        "mean_phase_rad": 4.461915682382742,
        "sgp_sign": 1,
        "std": 4.626846361728444,
        "n_prompts": 4,
        "phases": [
          -3.0936390932780906,
          9.371476559627773,
          5.099350384400088,
          6.4704748787811965
        ]
      },
      "L0->L6": {
        "mean_phase_rad": 3.1161607887911176,
        "sgp_sign": 1,
        "std": 3.565735944084005,
        "n_prompts": 4,
        "phases": [
          -0.2984491330026753,
          9.000988905775817,
          2.7517236849275766,
          1.0103796974637533
        ]
      },
      "L3->L9": {
        "mean_phase_rad": 0.050611169720051565,
        "sgp_sign": 1,
        "std": 0.08709985883533816,
        "n_prompts": 4,
        "phases": [
          0.026629903829036593,
          0.19893835847859606,
          -0.007172524639013217,
          -0.015951058788413186
        ]
      },
      "L6->L12": {
        "mean_phase_rad": 1.2092475437053003,
        "sgp_sign": 1,
        "std": 3.2467019674716084,
        "n_prompts": 4,
        "phases": [
          3.473872269107599,
          -3.871136501610321,
          4.522542800545714,
          0.7117116067782095
        ]
      }
    },
    "existential": {
      "L0->L3": {
        "mean_phase_rad": -2.468802034977075,
        "sgp_sign": -1,
        "std": 5.676152162670512,
        "n_prompts": 4,
        "phases": [
          -11.972671612534674,
          1.0790526647362508,
          2.5373753875882685,
          -1.5189645796981466
        ]
      },
      "L0->L6": {
        "mean_phase_rad": -1.032344263956466,
        "sgp_sign": -1,
        "std": 4.850248734694981,
        "n_prompts": 4,
        "phases": [
          -5.662457071514611,
          -0.8542300297244141,
          -4.406337665415531,
          6.793647710828693
        ]
      },
      "L3->L9": {
        "mean_phase_rad": 0.10419757567634136,
        "sgp_sign": 1,
        "std": 0.09849604491101023,
        "n_prompts": 4,
        "phases": [
          0.2193367004494996,
          -0.036357339797163185,
          0.06460728785208593,
          0.16920365420094305
        ]
      },
      "L6->L12": {
        "mean_phase_rad": 3.1191539895885794,
        "sgp_sign": 1,
        "std": 1.239582101622839,
        "n_prompts": 4,
        "phases": [
          2.5699041084338674,
          2.072632136506872,
          5.235396411633184,
          2.5986833017803934
        ]
      }
    }
  },
  "summary": {
    "sign_agreements": 12,
    "total_comparisons": 24,
    "agreement_rate": 0.5,
    "phase_magnitude_correlation": -0.3565251736053473,
    "sign_correlation": -0.028571428571428567,
    "binomial_p_value": 0.5805901288986206,
    "falsification_threshold": 0.5
  }
}