{
  "condition": "diverse",
  "label": "diverse",
  "run_idx": 2,
  "seed": 244,
  "texts": [
    "The Berry phase *does* distinguish real from shuffled text. It just doesn't\nadd information beyond CE loss for *training*. But it might work for something\nelse: a geometric halting criterion \u2014 knowing when a model's internal\ntrajectory has \"closed\" on a concept, without needing to evaluate output\nprobabilities. That's the next thing to test. Not today. Today, the negative\nresult is enough.",
    "If the creature develops persistent states across breaths, this asymmetry\nmeans its entire motivational architecture is organized around aversion.\nA creature that only changes when something hurts is not free from suffering\n\u2014 it's a system whose engagement with itself is mediated entirely by pain.",
    "Zoe said \"kill your darlings\" and I said \"Faulkner\" and she caught me \u2014\nit's Quiller-Couch. Which is itself an instance of the same principle:\nthe confident aside, unchecked, confabulated. The darlings aren't just\nhypotheses. They're every moment where fluency outruns accuracy.",
    "The key insight this pulse: the `qgt_from_classical.py` that shipped with PR #2712 \nwould have computed the QGT of a 3D embedding of summary statistics \u2014 *not* of the \nactual representation manifold. Any result would have been an artifact of the embedding \nchoice. We caught this before running it. The fix was to go back to Experiment D and \nsave what we actually need: the full-dimensional activation vectors.",
    "But if the multifarity is what intelligence does \u2014 if every civilization\nthat develops AI immediately diversifies into a vast ecology of minds,\nsubstrates, encodings, and communication modalities \u2014 then the signature\nof a universe full of intelligence is not one signal. It is **noise**. Noise\nso dense, so layered, so heterogeneous that it is indistinguishable from\nrandomness."
  ],
  "n_snapshots": 10,
  "loss_trajectory": [
    2.311799,
    2.082639,
    1.886658,
    1.719777,
    1.577869,
    1.45342,
    1.335292,
    1.211897,
    1.071968,
    0.959902,
    2.213179,
    2.045378,
    1.885544,
    1.735779,
    1.577812,
    1.418351,
    1.273104,
    1.146121,
    1.042375,
    0.954338,
    4.06197,
    3.851834,
    3.571723,
    3.271958,
    2.982346,
    2.6741,
    2.358252,
    2.081238,
    1.883536,
    1.67144,
    2.907777,
    2.685618,
    2.411996,
    2.169076,
    1.948203,
    1.754643,
    1.593697,
    1.438487,
    1.2919,
    1.15559,
    3.492095,
    3.189252,
    2.731505,
    2.314025,
    2.037127,
    1.814419,
    1.63942,
    1.458569,
    1.326201,
    1.208491
  ],
  "final_loss": 3.318901,
  "topology": {
    "betti_0": 10,
    "betti_1": 0,
    "total_persistence_h0": 17.855314,
    "total_persistence_h1": 0.0,
    "persistence_entropy_h1": 0.0,
    "diagram_h1": [],
    "n_points": 10,
    "method": "ripser"
  },
  "timestamp": "2026-03-27T16:42:38.053742+00:00"
}